{
  "dataAsOf": "2025-12-01",
  "frontOffices": [
    {
      "teamId": "ATL",
      "gmName": "Onsi Saleh",
      "presidentName": "Onsi Saleh",
      "competence": "Average",
      "tradeEvaluationSkill": 58,
      "negotiationSkill": 55,
      "scoutingAccuracy": 62,
      "tradeAggression": "Moderate",
      "teamSituation": "PlayoffBubble",
      "patience": 55,
      "riskTolerance": 50,
      "willingToTakeOnBadContracts": false,
      "willingToIncludePicks": true,
      "leakTendency": "Average",
      "yearsInPosition": 1,
      "isFormerPlayer": false
    },
    {
      "teamId": "BOS",
      "gmName": "Brad Stevens",
      "presidentName": "Brad Stevens",
      "competence": "Elite",
      "tradeEvaluationSkill": 92,
      "negotiationSkill": 88,
      "scoutingAccuracy": 85,
      "tradeAggression": "Moderate",
      "teamSituation": "Championship",
      "patience": 80,
      "riskTolerance": 45,
      "willingToTakeOnBadContracts": true,
      "willingToIncludePicks": false,
      "leakTendency": "TightLipped",
      "yearsInPosition": 4,
      "isFormerPlayer": false
    },
    {
      "teamId": "BKN",
      "gmName": "Sean Marks",
      "presidentName": "Sean Marks",
      "competence": "Good",
      "tradeEvaluationSkill": 72,
      "negotiationSkill": 70,
      "scoutingAccuracy": 75,
      "tradeAggression": "Moderate",
      "teamSituation": "StuckInMiddle",
      "patience": 70,
      "riskTolerance": 50,
      "willingToTakeOnBadContracts": true,
      "willingToIncludePicks": false,
      "leakTendency": "TightLipped",
      "yearsInPosition": 9,
      "isFormerPlayer": true
    },
    {
      "teamId": "CHA",
      "gmName": "Jeff Peterson",
      "presidentName": "Jeff Peterson",
      "competence": "Average",
      "tradeEvaluationSkill": 55,
      "negotiationSkill": 52,
      "scoutingAccuracy": 58,
      "tradeAggression": "Conservative",
      "teamSituation": "Rebuilding",
      "patience": 60,
      "riskTolerance": 40,
      "willingToTakeOnBadContracts": true,
      "willingToIncludePicks": false,
      "leakTendency": "Average",
      "yearsInPosition": 2,
      "isFormerPlayer": false
    },
    {
      "teamId": "CHI",
      "gmName": "Marc Eversley",
      "presidentName": "Arturas Karnisovas",
      "competence": "Average",
      "tradeEvaluationSkill": 58,
      "negotiationSkill": 55,
      "scoutingAccuracy": 60,
      "tradeAggression": "Conservative",
      "teamSituation": "PlayoffBubble",
      "patience": 55,
      "riskTolerance": 45,
      "willingToTakeOnBadContracts": false,
      "willingToIncludePicks": true,
      "leakTendency": "Average",
      "yearsInPosition": 5,
      "isFormerPlayer": false
    },
    {
      "teamId": "CLE",
      "gmName": "Mike Gansey",
      "presidentName": "Koby Altman",
      "competence": "Good",
      "tradeEvaluationSkill": 75,
      "negotiationSkill": 72,
      "scoutingAccuracy": 78,
      "tradeAggression": "Moderate",
      "teamSituation": "Championship",
      "patience": 70,
      "riskTolerance": 50,
      "willingToTakeOnBadContracts": false,
      "willingToIncludePicks": true,
      "leakTendency": "TightLipped",
      "yearsInPosition": 3,
      "isFormerPlayer": false
    },
    {
      "teamId": "DAL",
      "gmName": "Nico Harrison",
      "presidentName": "Nico Harrison",
      "competence": "Good",
      "tradeEvaluationSkill": 70,
      "negotiationSkill": 75,
      "scoutingAccuracy": 68,
      "tradeAggression": "Aggressive",
      "teamSituation": "PlayoffBubble",
      "patience": 40,
      "riskTolerance": 70,
      "willingToTakeOnBadContracts": false,
      "willingToIncludePicks": true,
      "leakTendency": "Average",
      "yearsInPosition": 4,
      "isFormerPlayer": false
    },
    {
      "teamId": "DEN",
      "gmName": "Calvin Booth",
      "presidentName": "Calvin Booth",
      "competence": "Good",
      "tradeEvaluationSkill": 75,
      "negotiationSkill": 70,
      "scoutingAccuracy": 78,
      "tradeAggression": "Conservative",
      "teamSituation": "Championship",
      "patience": 75,
      "riskTolerance": 45,
      "willingToTakeOnBadContracts": false,
      "willingToIncludePicks": false,
      "leakTendency": "TightLipped",
      "yearsInPosition": 3,
      "isFormerPlayer": true
    },
    {
      "teamId": "DET",
      "gmName": "Trajan Langdon",
      "presidentName": "Trajan Langdon",
      "competence": "Elite",
      "tradeEvaluationSkill": 88,
      "negotiationSkill": 85,
      "scoutingAccuracy": 90,
      "tradeAggression": "Moderate",
      "teamSituation": "Rebuilding",
      "patience": 80,
      "riskTolerance": 55,
      "willingToTakeOnBadContracts": true,
      "willingToIncludePicks": false,
      "leakTendency": "TightLipped",
      "yearsInPosition": 2,
      "isFormerPlayer": true
    },
    {
      "teamId": "GSW",
      "gmName": "Mike Dunleavy Jr.",
      "presidentName": "Mike Dunleavy Jr.",
      "competence": "Good",
      "tradeEvaluationSkill": 75,
      "negotiationSkill": 72,
      "scoutingAccuracy": 78,
      "tradeAggression": "Moderate",
      "teamSituation": "Contending",
      "patience": 65,
      "riskTolerance": 50,
      "willingToTakeOnBadContracts": false,
      "willingToIncludePicks": true,
      "leakTendency": "TightLipped",
      "yearsInPosition": 2,
      "isFormerPlayer": true
    },
    {
      "teamId": "HOU",
      "gmName": "Rafael Stone",
      "presidentName": "Rafael Stone",
      "competence": "Good",
      "tradeEvaluationSkill": 78,
      "negotiationSkill": 80,
      "scoutingAccuracy": 75,
      "tradeAggression": "Moderate",
      "teamSituation": "Rebuilding",
      "patience": 85,
      "riskTolerance": 55,
      "willingToTakeOnBadContracts": true,
      "willingToIncludePicks": false,
      "leakTendency": "TightLipped",
      "yearsInPosition": 5,
      "isFormerPlayer": false
    },
    {
      "teamId": "IND",
      "gmName": "Chad Buchanan",
      "presidentName": "Kevin Pritchard",
      "competence": "Elite",
      "tradeEvaluationSkill": 85,
      "negotiationSkill": 82,
      "scoutingAccuracy": 88,
      "tradeAggression": "Moderate",
      "teamSituation": "Contending",
      "patience": 70,
      "riskTolerance": 55,
      "willingToTakeOnBadContracts": false,
      "willingToIncludePicks": true,
      "leakTendency": "TightLipped",
      "yearsInPosition": 8,
      "isFormerPlayer": false
    },
    {
      "teamId": "LAC",
      "gmName": "Trent Redden",
      "presidentName": "Lawrence Frank",
      "competence": "Average",
      "tradeEvaluationSkill": 62,
      "negotiationSkill": 58,
      "scoutingAccuracy": 65,
      "tradeAggression": "Moderate",
      "teamSituation": "StuckInMiddle",
      "patience": 50,
      "riskTolerance": 50,
      "willingToTakeOnBadContracts": false,
      "willingToIncludePicks": true,
      "leakTendency": "Average",
      "yearsInPosition": 2,
      "isFormerPlayer": false
    },
    {
      "teamId": "LAL",
      "gmName": "Rob Pelinka",
      "presidentName": "Rob Pelinka",
      "competence": "Elite",
      "tradeEvaluationSkill": 82,
      "negotiationSkill": 90,
      "scoutingAccuracy": 75,
      "tradeAggression": "Aggressive",
      "teamSituation": "Contending",
      "patience": 45,
      "riskTolerance": 70,
      "willingToTakeOnBadContracts": false,
      "willingToIncludePicks": true,
      "leakTendency": "Average",
      "yearsInPosition": 8,
      "isFormerPlayer": false
    },
    {
      "teamId": "MEM",
      "gmName": "Zach Kleiman",
      "presidentName": "Zach Kleiman",
      "competence": "Good",
      "tradeEvaluationSkill": 78,
      "negotiationSkill": 75,
      "scoutingAccuracy": 80,
      "tradeAggression": "Moderate",
      "teamSituation": "Contending",
      "patience": 70,
      "riskTolerance": 55,
      "willingToTakeOnBadContracts": false,
      "willingToIncludePicks": false,
      "leakTendency": "TightLipped",
      "yearsInPosition": 6,
      "isFormerPlayer": false
    },
    {
      "teamId": "MIA",
      "gmName": "Andy Elisburg",
      "presidentName": "Pat Riley",
      "competence": "Good",
      "tradeEvaluationSkill": 75,
      "negotiationSkill": 78,
      "scoutingAccuracy": 72,
      "tradeAggression": "Aggressive",
      "teamSituation": "PlayoffBubble",
      "patience": 50,
      "riskTolerance": 65,
      "willingToTakeOnBadContracts": false,
      "willingToIncludePicks": true,
      "leakTendency": "TightLipped",
      "yearsInPosition": 12,
      "isFormerPlayer": false
    },
    {
      "teamId": "MIL",
      "gmName": "Jon Horst",
      "presidentName": "Jon Horst",
      "competence": "Good",
      "tradeEvaluationSkill": 75,
      "negotiationSkill": 72,
      "scoutingAccuracy": 70,
      "tradeAggression": "Moderate",
      "teamSituation": "Contending",
      "patience": 60,
      "riskTolerance": 55,
      "willingToTakeOnBadContracts": false,
      "willingToIncludePicks": true,
      "leakTendency": "TightLipped",
      "yearsInPosition": 8,
      "isFormerPlayer": false
    },
    {
      "teamId": "MIN",
      "gmName": "Matt Lloyd",
      "presidentName": "Tim Connelly",
      "competence": "Good",
      "tradeEvaluationSkill": 72,
      "negotiationSkill": 70,
      "scoutingAccuracy": 75,
      "tradeAggression": "Moderate",
      "teamSituation": "Contending",
      "patience": 65,
      "riskTolerance": 50,
      "willingToTakeOnBadContracts": false,
      "willingToIncludePicks": true,
      "leakTendency": "TightLipped",
      "yearsInPosition": 3,
      "isFormerPlayer": false
    },
    {
      "teamId": "NOP",
      "gmName": "Bryson Graham",
      "presidentName": "David Griffin",
      "competence": "Average",
      "tradeEvaluationSkill": 60,
      "negotiationSkill": 55,
      "scoutingAccuracy": 62,
      "tradeAggression": "Conservative",
      "teamSituation": "StuckInMiddle",
      "patience": 55,
      "riskTolerance": 45,
      "willingToTakeOnBadContracts": false,
      "willingToIncludePicks": true,
      "leakTendency": "Average",
      "yearsInPosition": 1,
      "isFormerPlayer": false
    },
    {
      "teamId": "NYK",
      "gmName": "Gersson Rosas",
      "presidentName": "Leon Rose",
      "competence": "Good",
      "tradeEvaluationSkill": 72,
      "negotiationSkill": 75,
      "scoutingAccuracy": 70,
      "tradeAggression": "Aggressive",
      "teamSituation": "Contending",
      "patience": 45,
      "riskTolerance": 65,
      "willingToTakeOnBadContracts": false,
      "willingToIncludePicks": true,
      "leakTendency": "Leaky",
      "yearsInPosition": 2,
      "isFormerPlayer": false
    },
    {
      "teamId": "OKC",
      "gmName": "Sam Presti",
      "presidentName": "Sam Presti",
      "competence": "Elite",
      "tradeEvaluationSkill": 95,
      "negotiationSkill": 92,
      "scoutingAccuracy": 95,
      "tradeAggression": "Moderate",
      "teamSituation": "Championship",
      "patience": 95,
      "riskTolerance": 55,
      "willingToTakeOnBadContracts": true,
      "willingToIncludePicks": false,
      "leakTendency": "TightLipped",
      "yearsInPosition": 18,
      "isFormerPlayer": false
    },
    {
      "teamId": "ORL",
      "gmName": "John Hammond",
      "presidentName": "Jeff Weltman",
      "competence": "Good",
      "tradeEvaluationSkill": 72,
      "negotiationSkill": 68,
      "scoutingAccuracy": 78,
      "tradeAggression": "Conservative",
      "teamSituation": "Contending",
      "patience": 75,
      "riskTolerance": 45,
      "willingToTakeOnBadContracts": false,
      "willingToIncludePicks": false,
      "leakTendency": "TightLipped",
      "yearsInPosition": 8,
      "isFormerPlayer": false
    },
    {
      "teamId": "PHI",
      "gmName": "Elton Brand",
      "presidentName": "Daryl Morey",
      "competence": "Average",
      "tradeEvaluationSkill": 58,
      "negotiationSkill": 55,
      "scoutingAccuracy": 65,
      "tradeAggression": "Aggressive",
      "teamSituation": "PlayoffBubble",
      "patience": 40,
      "riskTolerance": 65,
      "willingToTakeOnBadContracts": false,
      "willingToIncludePicks": true,
      "leakTendency": "Leaky",
      "yearsInPosition": 6,
      "isFormerPlayer": true
    },
    {
      "teamId": "PHX",
      "gmName": "James Jones",
      "presidentName": "James Jones",
      "competence": "Average",
      "tradeEvaluationSkill": 60,
      "negotiationSkill": 62,
      "scoutingAccuracy": 58,
      "tradeAggression": "Aggressive",
      "teamSituation": "PlayoffBubble",
      "patience": 35,
      "riskTolerance": 75,
      "willingToTakeOnBadContracts": false,
      "willingToIncludePicks": true,
      "leakTendency": "Leaky",
      "yearsInPosition": 8,
      "isFormerPlayer": true
    },
    {
      "teamId": "POR",
      "gmName": "Joe Cronin",
      "presidentName": "Joe Cronin",
      "competence": "Average",
      "tradeEvaluationSkill": 62,
      "negotiationSkill": 65,
      "scoutingAccuracy": 60,
      "tradeAggression": "Moderate",
      "teamSituation": "Rebuilding",
      "patience": 70,
      "riskTolerance": 50,
      "willingToTakeOnBadContracts": true,
      "willingToIncludePicks": false,
      "leakTendency": "Average",
      "yearsInPosition": 4,
      "isFormerPlayer": false
    },
    {
      "teamId": "SAC",
      "gmName": "Monte McNair",
      "presidentName": "Monte McNair",
      "competence": "Good",
      "tradeEvaluationSkill": 72,
      "negotiationSkill": 70,
      "scoutingAccuracy": 68,
      "tradeAggression": "Moderate",
      "teamSituation": "PlayoffBubble",
      "patience": 60,
      "riskTolerance": 55,
      "willingToTakeOnBadContracts": false,
      "willingToIncludePicks": true,
      "leakTendency": "TightLipped",
      "yearsInPosition": 5,
      "isFormerPlayer": false
    },
    {
      "teamId": "SAS",
      "gmName": "Brian Wright",
      "presidentName": "Gregg Popovich",
      "competence": "Good",
      "tradeEvaluationSkill": 72,
      "negotiationSkill": 68,
      "scoutingAccuracy": 75,
      "tradeAggression": "Conservative",
      "teamSituation": "Rebuilding",
      "patience": 85,
      "riskTolerance": 45,
      "willingToTakeOnBadContracts": true,
      "willingToIncludePicks": false,
      "leakTendency": "TightLipped",
      "yearsInPosition": 6,
      "isFormerPlayer": false
    },
    {
      "teamId": "TOR",
      "gmName": "Bobby Webster",
      "presidentName": "Masai Ujiri",
      "competence": "Good",
      "tradeEvaluationSkill": 70,
      "negotiationSkill": 72,
      "scoutingAccuracy": 75,
      "tradeAggression": "Moderate",
      "teamSituation": "StuckInMiddle",
      "patience": 65,
      "riskTolerance": 50,
      "willingToTakeOnBadContracts": false,
      "willingToIncludePicks": true,
      "leakTendency": "TightLipped",
      "yearsInPosition": 8,
      "isFormerPlayer": false
    },
    {
      "teamId": "UTA",
      "gmName": "Justin Zanik",
      "presidentName": "Danny Ainge",
      "competence": "Good",
      "tradeEvaluationSkill": 75,
      "negotiationSkill": 78,
      "scoutingAccuracy": 72,
      "tradeAggression": "Moderate",
      "teamSituation": "Rebuilding",
      "patience": 80,
      "riskTolerance": 50,
      "willingToTakeOnBadContracts": true,
      "willingToIncludePicks": false,
      "leakTendency": "TightLipped",
      "yearsInPosition": 5,
      "isFormerPlayer": false
    },
    {
      "teamId": "WAS",
      "gmName": "Will Dawkins",
      "presidentName": "Michael Winger",
      "competence": "Average",
      "tradeEvaluationSkill": 55,
      "negotiationSkill": 52,
      "scoutingAccuracy": 58,
      "tradeAggression": "Conservative",
      "teamSituation": "Rebuilding",
      "patience": 65,
      "riskTolerance": 40,
      "willingToTakeOnBadContracts": true,
      "willingToIncludePicks": false,
      "leakTendency": "Average",
      "yearsInPosition": 2,
      "isFormerPlayer": false
    }
  ]
}
